prdnn/__init__.py
prdnn/ddnn.py
prdnn/ft_repair.py
prdnn/provable_repair.py
prdnn-1.0.dist-info/LICENSE
prdnn-1.0.dist-info/METADATA
prdnn-1.0.dist-info/WHEEL
prdnn-1.0.dist-info/top_level.txt
prdnn-1.0.dist-info/RECORD
