Metadata-Version: 2.1
Name: prdnn
Version: 1.0
Summary: Provable Repair of DNNs
Home-page: https://github.com/95616ARG/PRDNN
Author: Matthew Sotoudeh and Aditya V. Thakur
Author-email: masotoudeh@ucdavis.edu, avthakur@ucdavis.edu
Maintainer: Matthew Sotoudeh and Aditya V. Thakur
Maintainer-email: masotoudeh@ucdavis.edu, avthakur@ucdavis.edu
License: MIT
Keywords: class,attribute,boilerplate
Platform: UNKNOWN
Classifier: Development Status :: 5 - Production/Stable
Classifier: Intended Audience :: Developers
Classifier: Natural Language :: English
Classifier: License :: OSI Approved :: MIT License
Classifier: Operating System :: OS Independent
Classifier: Programming Language :: Python
Classifier: Programming Language :: Python :: 2
Classifier: Programming Language :: Python :: 2.7
Classifier: Programming Language :: Python :: 3
Classifier: Programming Language :: Python :: 3.3
Classifier: Programming Language :: Python :: 3.4
Classifier: Programming Language :: Python :: 3.5
Classifier: Programming Language :: Python :: 3.6
Classifier: Programming Language :: Python :: 3.7
Classifier: Programming Language :: Python :: Implementation :: CPython
Classifier: Programming Language :: Python :: Implementation :: PyPy
Classifier: Topic :: Software Development :: Libraries :: Python Modules
Requires-Dist: torch
Requires-Dist: pysyrenn (>=1.1)
Requires-Dist: scipy
